LICENSE.txt
README.md
setup.cfg
setup.py
examples/__init__.py
examples/chat_bot.py
examples/desktop_authenticator.py
examples/storehouse.py
steampy/__init__.py
steampy/chat.py
steampy/client.py
steampy/confirmation.py
steampy/exceptions.py
steampy/guard.py
steampy/login.py
steampy/market.py
steampy/models.py
steampy/utils.py
steampy_proxy.egg-info/PKG-INFO
steampy_proxy.egg-info/SOURCES.txt
steampy_proxy.egg-info/dependency_links.txt
steampy_proxy.egg-info/requires.txt
steampy_proxy.egg-info/top_level.txt
test/__init__.py
test/test_client.py
test/test_guard.py
test/test_market.py
test/test_utils.py